t3py/__init__.py
t3py/__main__.py
t3py/commands/auth_check.py
t3py-0.4.1.dist-info/licenses/LICENSE
t3py-0.4.1.dist-info/METADATA
t3py-0.4.1.dist-info/WHEEL
t3py-0.4.1.dist-info/entry_points.txt
t3py-0.4.1.dist-info/top_level.txt
t3py-0.4.1.dist-info/RECORD
